pegs/__init__.py
pegs/bedtools.py
pegs/cli.py
pegs/intervals.py
pegs/outputs.py
pegs/pegs.py
pegs/utils.py
pegs-0.6.6.data/data/pegs-0.6.6/refGene_hg38_120719_intervals.bed
pegs-0.6.6.data/data/pegs-0.6.6/refGene_mm10_120719_intervals.bed
pegs-0.6.6.dist-info/LICENSE
pegs-0.6.6.dist-info/METADATA
pegs-0.6.6.dist-info/WHEEL
pegs-0.6.6.dist-info/entry_points.txt
pegs-0.6.6.dist-info/top_level.txt
pegs-0.6.6.dist-info/RECORD
