Metadata-Version: 2.1
Name: pegs
Version: 0.6.6
Summary: Peak-set Enrichment of Gene-Sets (PEGS)
Home-page: https://github.com/fls-bioinformatics-core/pegs
Author: Mudassar Iqbal, Peter Briggs
Maintainer: Peter Briggs
Maintainer-email: peter.briggs@manchester.ac.uk
License: BSD-3-Clause
Keywords: PEGS
Classifier: Development Status :: 3 - Alpha
Classifier: Intended Audience :: Science/Research
Classifier: Environment :: Console
Classifier: License :: OSI Approved :: BSD License
Classifier: Operating System :: POSIX
Classifier: Topic :: Scientific/Engineering :: Bio-Informatics
Classifier: Natural Language :: English
Classifier: Programming Language :: Python :: 3
Classifier: Programming Language :: Python :: 3.6
Classifier: Programming Language :: Python :: 3.7
Classifier: Programming Language :: Python :: 3.8
Classifier: Programming Language :: Python :: 3.9
License-File: LICENSE
Requires-Dist: numpy ==1.19.5
Requires-Dist: scipy ==1.5.4
Requires-Dist: matplotlib ==3.3.4
Requires-Dist: pillow ==8.1.1
Requires-Dist: seaborn ==0.11.1
Requires-Dist: xlsxwriter ==3.1.9
Requires-Dist: pathlib2
